tayuya/__init__.py
tayuya/constants.py
tayuya/exceptions.py
tayuya/midi.py
tayuya/tabs.py
tayuya-0.0.4.dist-info/LICENSE.md
tayuya-0.0.4.dist-info/METADATA
tayuya-0.0.4.dist-info/WHEEL
tayuya-0.0.4.dist-info/top_level.txt
tayuya-0.0.4.dist-info/RECORD
