Metadata-Version: 2.1
Name: tayuya
Version: 0.0.4
Summary: MIDI to guitar tabs generator
Home-page: https://github.com/vipul-sharma20/tayuya
Author: Vipul Sharma
Author-email: vipul.sharma20@gmail.com
License: UNKNOWN
Platform: UNKNOWN
Classifier: Programming Language :: Python :: 3
Classifier: License :: OSI Approved :: MIT License
Classifier: Operating System :: OS Independent
Requires-Python: >=3.6
Requires-Dist: mido
Requires-Dist: music21
